xbackup/__init__.py
xbackup/commands/__init__.py
xbackup/commands/backup.py
xbackup/utils/__init__.py
xbackup-0.1.dist-info/LICENSE
xbackup-0.1.dist-info/METADATA
xbackup-0.1.dist-info/WHEEL
xbackup-0.1.dist-info/entry_points.txt
xbackup-0.1.dist-info/top_level.txt
xbackup-0.1.dist-info/zip-safe
xbackup-0.1.dist-info/RECORD
