Metadata-Version: 2.1
Name: xbackup
Version: 0.1
Summary: Backup. Restore.
Home-page: https://github.com/bondbox/xbackup-python
Author: Mingzhe Zou
Author-email: zoumingzhe@outlook.com
License: MIT
Project-URL: Source Code, https://github.com/bondbox/xbackup
Project-URL: Bug Tracker, https://github.com/bondbox/xbackup/issues
Project-URL: Documentation, https://github.com/bondbox/xbackup
Keywords: backup,restore
Platform: any
Classifier: Programming Language :: Python
Classifier: Programming Language :: Python :: 3
Requires-Python: >=3.6
License-File: LICENSE
Requires-Dist: xarg-python (>=0.10)
